neuroglyph_16bit.py
neuroglyph_eco.py
neuroglyph_fast.py
neuroglyph_hyper.py
neuroglyph_neural.py
neuroglyph_omega.py
neuroglyph_progressive.py
neuroglyph_quantum.py
neuroglyph_simd.py
neuroglyph_ultra.py
neuroglyph_video.py
neuroglyph-2.3.1.dist-info/licenses/LICENSE
tests/__init__.py
tests/test_16bit.py
tests/test_neuroglyph.py
neuroglyph-2.3.1.dist-info/METADATA
neuroglyph-2.3.1.dist-info/WHEEL
neuroglyph-2.3.1.dist-info/top_level.txt
neuroglyph-2.3.1.dist-info/RECORD
