Metadata-Version: 2.4
Name: neuroglyph
Version: 2.3.1
Summary: Energy-efficient lossless compression optimized for screen recording, UI screenshots, and synthetic content
Home-page: https://github.com/yourusername/neuroglyph
Author: NeuroGlyph Contributors
Author-email: Benjamin Hanquier <bhanquier@users.noreply.github.com>
License-Expression: MIT
Project-URL: Homepage, https://github.com/bhanquier/neuroGlyph
Project-URL: Repository, https://github.com/bhanquier/neuroGlyph
Project-URL: Documentation, https://github.com/bhanquier/neuroGlyph#readme
Project-URL: Bug Tracker, https://github.com/bhanquier/neuroGlyph/issues
Project-URL: Changelog, https://github.com/bhanquier/neuroGlyph/blob/main/CHANGELOG.md
Project-URL: Releases, https://github.com/bhanquier/neuroGlyph/releases
Keywords: compression,lossless,png,image-processing,video-codec,energy-efficient,simd,neural-compression,webassembly
Classifier: Development Status :: 4 - Beta
Classifier: Intended Audience :: Developers
Classifier: Intended Audience :: Science/Research
Classifier: Operating System :: OS Independent
Classifier: Programming Language :: Python :: 3
Classifier: Programming Language :: Python :: 3.8
Classifier: Programming Language :: Python :: 3.9
Classifier: Programming Language :: Python :: 3.10
Classifier: Programming Language :: Python :: 3.11
Classifier: Programming Language :: Python :: 3.12
Classifier: Topic :: Multimedia :: Graphics
Classifier: Topic :: Multimedia :: Video
Classifier: Topic :: Scientific/Engineering :: Image Processing
Classifier: Topic :: System :: Archiving :: Compression
Requires-Python: >=3.8
License-File: LICENSE
Requires-Dist: numpy>=1.24.0
Requires-Dist: Pillow>=10.0.0
Provides-Extra: dev
Requires-Dist: pytest>=7.4.0; extra == "dev"
Requires-Dist: pytest-cov>=4.1.0; extra == "dev"
Requires-Dist: psutil>=5.9.0; extra == "dev"
Provides-Extra: performance
Requires-Dist: numba>=0.58.0; extra == "performance"
Provides-Extra: benchmark
Requires-Dist: matplotlib>=3.7.0; extra == "benchmark"
Requires-Dist: psutil>=5.9.0; extra == "benchmark"
Provides-Extra: all
Requires-Dist: pytest>=7.4.0; extra == "all"
Requires-Dist: pytest-cov>=4.1.0; extra == "all"
Requires-Dist: psutil>=5.9.0; extra == "all"
Requires-Dist: matplotlib>=3.7.0; extra == "all"
Requires-Dist: numba>=0.58.0; extra == "all"
Dynamic: author
Dynamic: home-page
Dynamic: license-file
Dynamic: requires-python
